{
  "main": {
    "id": "d7056f7b92ce7d78",
    "type": "split",
    "children": [
      {
        "id": "ccf5af3a8d7abd16",
        "type": "tabs",
        "children": [
          {
            "id": "490769f4f6141ac2",
            "type": "leaf",
            "state": {
              "type": "empty",
              "state": {}
            }
          }
        ]
      }
    ],
    "direction": "vertical"
  },
  "left": {
    "id": "e242ae0d95ceef67",
    "type": "split",
    "children": [
      {
        "id": "4b93870f0a10c54c",
        "type": "tabs",
        "children": [
          {
            "id": "0ca69e5f8aef4893",
            "type": "leaf",
            "state": {
              "type": "file-explorer",
              "state": {
                "sortOrder": "alphabetical"
              }
            }
          },
          {
            "id": "207f3861432d3c83",
            "type": "leaf",
            "state": {
              "type": "search",
              "state": {
                "query": "",
                "matchingCase": false,
                "explainSearch": false,
                "collapseAll": false,
                "extraContext": false,
                "sortOrder": "alphabetical"
              }
            }
          },
          {
            "id": "5dbfd89c90b9a66a",
            "type": "leaf",
            "state": {
              "type": "starred",
              "state": {}
            }
          }
        ]
      }
    ],
    "direction": "horizontal",
    "width": 413.5
  },
  "right": {
    "id": "4ff5ea5b0c17c316",
    "type": "split",
    "children": [
      {
        "id": "7c8a104d0dc1373d",
        "type": "tabs",
        "dimension": 68.85521885521885,
        "children": [
          {
            "id": "33d8f6e31c4d75f4",
            "type": "leaf",
            "state": {
              "type": "backlink",
              "state": {
                "collapseAll": false,
                "extraContext": false,
                "sortOrder": "alphabetical",
                "showSearch": false,
                "searchQuery": "",
                "backlinkCollapsed": false,
                "unlinkedCollapsed": false
              }
            }
          },
          {
            "id": "02ae006a1dabcb67",
            "type": "leaf",
            "state": {
              "type": "outgoing-link",
              "state": {
                "linksCollapsed": false,
                "unlinkedCollapsed": true
              }
            }
          },
          {
            "id": "664308e2baf8e863",
            "type": "leaf",
            "state": {
              "type": "tag",
              "state": {
                "sortOrder": "frequency",
                "useHierarchy": true
              }
            }
          },
          {
            "id": "2341b65aa97a4258",
            "type": "leaf",
            "state": {
              "type": "advanced-tables-toolbar",
              "state": {}
            }
          },
          {
            "id": "546e865b0c38f6f4",
            "type": "leaf",
            "state": {
              "type": "outline",
              "state": {}
            }
          }
        ],
        "currentTab": 3
      },
      {
        "id": "91df1807ecc83f87",
        "type": "tabs",
        "dimension": 31.14478114478115,
        "children": [
          {
            "id": "9665daa99bf33c47",
            "type": "leaf",
            "state": {
              "type": "calendar",
              "state": {}
            }
          }
        ]
      }
    ],
    "direction": "horizontal",
    "width": 407.5,
    "collapsed": true
  },
  "left-ribbon": {
    "hiddenItems": {
      "table-editor-obsidian:Advanced Tables Toolbar": false,
      "switcher:Open quick switcher": false,
      "graph:Open graph view": false,
      "canvas:Create new canvas": false,
      "daily-notes:Open today's daily note": false,
      "templates:Insert template": false,
      "command-palette:Open command palette": false,
      "audio-recorder:Start/stop recording": false,
      "markdown-importer:Open format converter": false
    }
  },
  "active": "0ca69e5f8aef4893",
  "lastOpenFiles": [
    "readme.md",
    "assets/images/Pasted image 20230420123306.png",
    "assets/images/Pasted image 20230420123247.png",
    "assets/images/Pasted image 20230420123236.png",
    "_posts/2023/04/2023-04-20-hpc-for-fea.md",
    "_posts/2023/04",
    "README.md",
    "_posts/2023/01/2023-03-07-reduce-runtime-fem-simulations.md",
    "_posts/2023/01/2023-03-14-managing-your-time-as-researcher.md",
    "_posts/2022/Oct/2022-10-30-use-svg-in-html.md",
    "_posts/2021/2021-12-19-local-build-jekyll-website.md",
    "_posts/2021/2021-12-08-installing-petsc-complex.md",
    "_posts/2021/2021-11-08-nomenclature-in-latex.md",
    "_posts/2021/2021-01-18-build-python-project.md",
    "_posts/2021/2021-01-11-finding-fenics-commands.md",
    "_posts/2021/2021-01-05-setup-Typora.md",
    "_posts/2022/April/2022-04-02-add-search-jekyll-blog.md",
    "_posts/2022/April/2022-04-06-julia-jupyter-notebook.md",
    "_posts/2022/April/2022-04-30-latex-math-alphabets.md",
    "_posts/2022/April/2022-04-28-zotero-pcloud-box.md",
    "_posts/2022/April/2022-04-12-point-load-fenics.md",
    "_posts/2023/01",
    "_posts/2023",
    "pages/blog.md",
    "pages/support.md",
    "pages/terms-of-service.md",
    "pages/privacy-policy.md",
    "pages/cancellation.md",
    "pages/about.md",
    "assets/images/Recording 20230213192156.webm",
    "_posts/2022/Jan/2022-01-31-please-use-sparse-matrices.md",
    "_posts/2021/2021-03-12-matlab-direct.md"
  ]
}